fullAdder/fullAdder.v
module fullAdder(
  input a,
  input b,
  input cin,
  output sum,
  output carry
);
  assign sum = a ^ b ^ cin;
  assign carry = (a & b) | (b & cin) | (a & cin);
endmodule

fullAdder/tb_fullAdder.v
`timescale 1ns/1ps

module tb_fullAdder;
  reg a, b, cin;
  wire sum, carry;

  fullAdder uut(.a(a), .b(b), .cin(cin), .sum(sum), .carry(carry));

  initial begin
    $dumpfile("wave.vcd");
    $dumpvars(0, tb_fullAdder);
    $monitor("a=%b b=%b cin=%b => sum=%b carry=%b", a, b, cin, sum, carry);

    // Test all 8 input combinations
    a = 0; b = 0; cin = 0; #10;
    a = 0; b = 0; cin = 1; #10;
    a = 0; b = 1; cin = 0; #10;
    a = 0; b = 1; cin = 1; #10;
    a = 1; b = 0; cin = 0; #10;
    a = 1; b = 0; cin = 1; #10;
    a = 1; b = 1; cin = 0; #10;
    a = 1; b = 1; cin = 1; #10;

    $display("Test complete");
    $finish;
  end
endmodule

fullAdder/wave.vcd
$date
	Mon Jul 14 15:46:25 2025
$end
$version
	Icarus Verilog
$end
$timescale
	1ps
$end
$scope module tb_fullAdder $end
$var wire 1 ! sum $end
$var wire 1 " carry $end
$var reg 1 # a $end
$var reg 1 $ b $end
$var reg 1 % cin $end
$scope module uut $end
$var wire 1 # a $end
$var wire 1 $ b $end
$var wire 1 " carry $end
$var wire 1 % cin $end
$var wire 1 ! sum $end
$upscope $end
$upscope $end
$enddefinitions $end
$comment Show the parameter values. $end
$dumpall
$end
#0
$dumpvars
0%
0$
0#
0"
0!
$end
#10000
1!
1%
#20000
0%
1$
#30000
1"
0!
1%
#40000
0"
1!
0%
0$
1#
#50000
1"
0!
1%
#60000
0%
1$
#70000
1!
1%
